fancytable/__init__.py
fancytable-0.0.3.dist-info/DESCRIPTION.rst
fancytable-0.0.3.dist-info/METADATA
fancytable-0.0.3.dist-info/RECORD
fancytable-0.0.3.dist-info/WHEEL
fancytable-0.0.3.dist-info/metadata.json
fancytable-0.0.3.dist-info/top_level.txt
