Metadata-Version: 2.0
Name: fancytable
Version: 0.0.3
Summary: Display pd.DataFrame with fancy colors.
Home-page: https://github.com/yoshiso/fancytable.git
Author: Sho Yoshida
Author-email: nya060@gmail.com
License: MIT
Platform: UNKNOWN
